argumentsignature.py
argumentsignature-1.0.3.dist-info/licenses/LICENSE
argumentsignature-1.0.3.dist-info/METADATA
argumentsignature-1.0.3.dist-info/WHEEL
argumentsignature-1.0.3.dist-info/top_level.txt
argumentsignature-1.0.3.dist-info/RECORD
