Metadata-Version: 2.4
Name: argumentsignature
Version: 1.0.3
Summary: Argument classes for callable objects in Python.
Author-email: TahsinCr <TahsinCr@outlook.com>
License: MIT
Project-URL: Homepage, https://github.com/TahsinCr/python-argumentsignature
Project-URL: Source, https://github.com/TahsinCr/python-argumentsignature
Keywords: argument,signature,callable,xcollection
Classifier: Typing :: Typed
Classifier: Intended Audience :: Developers
Classifier: Programming Language :: Python :: 3
Classifier: License :: OSI Approved :: MIT License
Classifier: Operating System :: OS Independent
Requires-Python: >=3
License-File: LICENSE
Dynamic: license-file
